[
    {
        "_id": "0x173a",
        "todo": "Public why Republican improve chance course.",
        "text": "Account prevent third Democrat hard past same. Truth throw meeting walk focus yard central. Traditional brother PM themselves top former trouble.",
        "until": "2023-03-28 19:20:24",
        "user": "Matthew Ryan",
        "nodes": [
            "node-1",
            "node-3",
            "node-5"
        ]
    },
    {
        "_id": "0x173b",
        "todo": "Exist mean successful mission yard serious.",
        "text": "Require foot fast. Cause prove outside star.\nWould present ability court leave.\nLet eat edge idea. Stage operation suggest.\nFinish maybe if know bill black.",
        "until": "2026-03-21 21:49:46",
        "user": "Matthew Ryan",
        "nodes": [
            "node-1",
            "node-3",
            "node-5"
        ]
    },
    {
        "_id": "0x173c",
        "todo": "This remember office war group manager.",
        "text": "Arrive ahead even. Cup knowledge chair free toward.\nUp ready draw. Program last to idea hard billion for. Policy research region take recent indeed church anyone.",
        "until": "2028-12-02 08:29:00",
        "user": "Matthew Ryan",
        "nodes": [
            "node-1",
            "node-3",
            "node-5"
        ]
    },
    {
        "_id": "0x173d",
        "todo": "Under fight prepare ten indeed newspaper room.",
        "text": "Show economic growth good. Magazine money add range.\nParticular learn whether board fund. Free movie although his. Total yes mouth.",
        "until": "2023-01-18 15:35:05",
        "user": "Matthew Ryan",
        "nodes": [
            "node-1",
            "node-3",
            "node-5"
        ]
    },
    {
        "_id": "0x173e",
        "todo": "Management knowledge open site image investment different.",
        "text": "Require summer stock four really cost reduce cover. Such happen network billion series site one people.",
        "until": "2029-04-15 05:07:15",
        "user": "Matthew Ryan",
        "nodes": [
            "node-1",
            "node-3",
            "node-5"
        ]
    },
    {
        "_id": "0x173f",
        "todo": "Democrat fast pay wide up condition military.",
        "text": "President significant control east career skin concern. Three mouth practice interesting let try miss. Physical notice be song matter.\nSuccessful future let pick. Pay word case concern.",
        "until": "2024-07-10 11:30:29",
        "user": "Matthew Ryan",
        "nodes": [
            "node-1",
            "node-3",
            "node-5"
        ]
    }
]