[
    {
        "_id": "0x188f",
        "todo": "Office crime enough peace.",
        "text": "Candidate today imagine three plant. Politics own success writer blue.",
        "until": "2022-07-31 17:30:25",
        "user": "Alan Garcia",
        "nodes": [
            "node-1",
            "node-3",
            "node-5"
        ]
    },
    {
        "_id": "0x1890",
        "todo": "We ago discover toward.",
        "text": "Direction everything him senior board image light. Scene could population view determine name baby season. Reality series claim dark thing clear support.",
        "until": "2022-03-20 02:54:46",
        "user": "Alan Garcia",
        "nodes": [
            "node-1",
            "node-3",
            "node-5"
        ]
    },
    {
        "_id": "0x1891",
        "todo": "Discuss seat east central.",
        "text": "This box often response course. Carry her exist enough professional want successful news. Nothing reason appear investment.",
        "until": "2029-01-30 16:01:31",
        "user": "Alan Garcia",
        "nodes": [
            "node-1",
            "node-3",
            "node-5"
        ]
    },
    {
        "_id": "0x1892",
        "todo": "Find style write arm.",
        "text": "Reach boy space keep marriage. Listen so listen different six news bank.\nInstead represent want bank bed tree western another.",
        "until": "2023-04-14 01:36:05",
        "user": "Alan Garcia",
        "nodes": [
            "node-1",
            "node-3",
            "node-5"
        ]
    },
    {
        "_id": "0x1893",
        "todo": "Own school brother.",
        "text": "Bad find middle air affect church. Sometimes law grow successful summer could. Summer huge season mind technology somebody its.",
        "until": "2026-06-04 11:40:19",
        "user": "Alan Garcia",
        "nodes": [
            "node-1",
            "node-3",
            "node-5"
        ]
    }
]