[
    {
        "_id": "0x1cc6",
        "todo": "Rock main kid difference laugh.",
        "text": "Mind environment story school environment. Apply candidate ok media prove.",
        "until": "2029-09-18 05:36:45",
        "user": "Chloe Villegas",
        "nodes": [
            "node-1",
            "node-3",
            "node-5"
        ]
    },
    {
        "_id": "0x1cc7",
        "todo": "Eight officer measure hand morning medical those.",
        "text": "Camera visit brother grow soldier garden serve. Save final feel sometimes far space commercial trial. Deal special everybody care.",
        "until": "2021-05-25 01:20:05",
        "user": "Chloe Villegas",
        "nodes": [
            "node-1",
            "node-3",
            "node-5"
        ]
    },
    {
        "_id": "0x1cc8",
        "todo": "Along less consider down sort return cut.",
        "text": "True work size half. Prevent field past prove close. Cause brother a pay.\nDetermine free herself enough deal. Since mean budget become none tough.",
        "until": "2022-10-23 09:20:48",
        "user": "Chloe Villegas",
        "nodes": [
            "node-1",
            "node-3",
            "node-5"
        ]
    }
]