[
    {
        "_id": "0x1fe2",
        "todo": "Indicate focus side thing economic authority.",
        "text": "Wide professional me. Marriage perhaps action a national computer.\nMethod manager treat firm maybe person war. Could subject same good on. Street star wrong learn able blue.",
        "until": "2027-07-10 01:33:41",
        "user": "Travis Stephens",
        "nodes": [
            "node-1",
            "node-3",
            "node-5"
        ]
    },
    {
        "_id": "0x1fe3",
        "todo": "But against particular.",
        "text": "Full yet card else. Focus deep happy week.\nMarriage go effort adult. Exist institution glass leg million edge reveal free. Community stop shake deal left a life.",
        "until": "2022-02-24 05:01:40",
        "user": "Travis Stephens",
        "nodes": [
            "node-1",
            "node-3",
            "node-5"
        ]
    },
    {
        "_id": "0x1fe4",
        "todo": "Toward respond institution although would base half.",
        "text": "Age consumer around easy should blue. Population increase already science.\nFeel table leader world movement fill. Stop total head war organization free.",
        "until": "2027-12-26 12:54:01",
        "user": "Travis Stephens",
        "nodes": [
            "node-1",
            "node-3",
            "node-5"
        ]
    },
    {
        "_id": "0x1fe5",
        "todo": "Food end interesting thank.",
        "text": "Own girl recent our paper task. Explain common various build imagine.\nMan reveal simply. Hour affect scientist unit money through size.",
        "until": "2022-10-03 23:15:58",
        "user": "Travis Stephens",
        "nodes": [
            "node-1",
            "node-3",
            "node-5"
        ]
    }
]