[
    {
        "_id": "0x3429",
        "todo": "Ball home bill stay.",
        "text": "Fight fly discussion like surface born. Support anything Republican animal future method consider bed. Sound magazine yes despite free.",
        "until": "2029-06-22 09:36:53",
        "user": "Mr. Joshua Gray",
        "nodes": [
            "node-1",
            "node-3",
            "node-5"
        ]
    },
    {
        "_id": "0x342a",
        "todo": "Other what above short there.",
        "text": "Beat area property address wait join. Drop nor first without year board order.\nAnd goal only. News structure read what including. Pm magazine see rest task go situation hold.",
        "until": "2030-02-15 14:25:13",
        "user": "Mr. Joshua Gray",
        "nodes": [
            "node-1",
            "node-3",
            "node-5"
        ]
    },
    {
        "_id": "0x342b",
        "todo": "Every them street color impact actually choice.",
        "text": "Forward strategy argue mouth huge full. Among at which book guy. Mouth strong organization model become.",
        "until": "2022-09-08 15:43:26",
        "user": "Mr. Joshua Gray",
        "nodes": [
            "node-1",
            "node-3",
            "node-5"
        ]
    },
    {
        "_id": "0x342c",
        "todo": "Major painting toward end any product analysis.",
        "text": "Short world few moment office common enough. Home before wonder hit clearly rather. Dream girl win look because.",
        "until": "2021-10-05 18:39:28",
        "user": "Mr. Joshua Gray",
        "nodes": [
            "node-1",
            "node-3",
            "node-5"
        ]
    },
    {
        "_id": "0x342d",
        "todo": "Nice despite item take.",
        "text": "Direction action ahead statement your. Modern though fly must choose. Such moment morning piece.\nFind camera couple there view. Face health understand life interview.",
        "until": "2023-09-25 07:57:45",
        "user": "Mr. Joshua Gray",
        "nodes": [
            "node-1",
            "node-3",
            "node-5"
        ]
    },
    {
        "_id": "0x342e",
        "todo": "May debate sport performance apply determine key.",
        "text": "Forward anything police woman far similar moment. Purpose difference someone give skin. Agency hundred finish herself hospital.",
        "until": "2025-08-13 02:53:24",
        "user": "Mr. Joshua Gray",
        "nodes": [
            "node-1",
            "node-3",
            "node-5"
        ]
    }
]