[
    {
        "_id": "0x35c7",
        "todo": "Board animal two including notice.",
        "text": "Less the pattern inside. Add shake case near year. Professional method parent organization school.",
        "until": "2024-09-26 04:39:30",
        "user": "Mrs. Tiffany Chang",
        "nodes": [
            "node-1",
            "node-3",
            "node-5"
        ]
    },
    {
        "_id": "0x35c8",
        "todo": "Social present network summer ready and.",
        "text": "Your trial much he finish other keep. Color two exactly provide pattern important before. Pm per newspaper something.\nForm pull middle tend itself course ready way. Take speak specific season.",
        "until": "2029-02-24 16:44:40",
        "user": "Mrs. Tiffany Chang",
        "nodes": [
            "node-1",
            "node-3",
            "node-5"
        ]
    },
    {
        "_id": "0x35c9",
        "todo": "Paper too fear choice positive.",
        "text": "Prove maybe subject if day author. Job office owner all. Ground light financial explain. Us assume result store.",
        "until": "2027-11-07 04:08:34",
        "user": "Mrs. Tiffany Chang",
        "nodes": [
            "node-1",
            "node-3",
            "node-5"
        ]
    }
]