[
    {
        "_id": "0x427b",
        "todo": "Partner lay provide week whom ground mind.",
        "text": "Respond relate figure meet world. Life animal station a artist recent on blood. Language price line.\nFinish air light only cost final large. Protect image culture result consumer.",
        "until": "2029-11-07 16:10:18",
        "user": "Jacob Buck",
        "nodes": [
            "node-1",
            "node-3",
            "node-5"
        ]
    },
    {
        "_id": "0x427c",
        "todo": "Officer try leg citizen explain.",
        "text": "Air baby of value on attack argue. Event your girl someone until president miss. Investment type court significant.",
        "until": "2021-01-20 23:32:59",
        "user": "Jacob Buck",
        "nodes": [
            "node-1",
            "node-3",
            "node-5"
        ]
    },
    {
        "_id": "0x427d",
        "todo": "Require shake how name include program song conference.",
        "text": "Treatment make recent even together type common level. Ground job agent give. Garden technology thank goal.\nAnother bank including usually final can value. Morning I call all rock board leave.",
        "until": "2026-05-21 17:24:11",
        "user": "Jacob Buck",
        "nodes": [
            "node-1",
            "node-3",
            "node-5"
        ]
    }
]