[
    {
        "_id": "0x431d",
        "todo": "Discover often science individual remain deep.",
        "text": "Green discover measure economy. Low test final design machine. Seven building Democrat painting though.\nAudience top them standard work. Throw society international push determine.",
        "until": "2020-05-28 08:38:31",
        "user": "Joseph Williams",
        "nodes": [
            "node-1",
            "node-3",
            "node-5"
        ]
    },
    {
        "_id": "0x431e",
        "todo": "Environment all site remain.",
        "text": "You do president to fall stay. Something reveal real.\nRoad traditional factor prove and. Hope act single near surface on join. Since create position.",
        "until": "2027-06-23 03:38:18",
        "user": "Joseph Williams",
        "nodes": [
            "node-1",
            "node-3",
            "node-5"
        ]
    },
    {
        "_id": "0x431f",
        "todo": "Why agree into little son.",
        "text": "Environmental five also by ground painting. Prove page film none herself.\nMuch middle my trip trade officer over. Know theory building show early success. Great real on sea must including claim.",
        "until": "2028-08-14 14:10:48",
        "user": "Joseph Williams",
        "nodes": [
            "node-1",
            "node-3",
            "node-5"
        ]
    },
    {
        "_id": "0x4320",
        "todo": "Long moment well decision worry everyone according.",
        "text": "Time loss eight help continue. Reach suggest both. Cost baby prove.\nHeavy small it notice model.\nReality sister plant. Detail produce teach star voice check.",
        "until": "2021-08-23 15:58:21",
        "user": "Joseph Williams",
        "nodes": [
            "node-1",
            "node-3",
            "node-5"
        ]
    },
    {
        "_id": "0x4321",
        "todo": "Before agency leader be hair on.",
        "text": "Write else field admit some. Experience level fish along trade main this.\nAll painting price. Happen fast center watch foot.\nArtist real possible couple. Doctor cost cultural thus reason office all.",
        "until": "2028-01-28 02:30:08",
        "user": "Joseph Williams",
        "nodes": [
            "node-1",
            "node-3",
            "node-5"
        ]
    },
    {
        "_id": "0x4322",
        "todo": "Know do candidate go oil newspaper natural.",
        "text": "Loss federal two morning alone. Win thing medical purpose key.\nFire affect such realize listen bank discover. Adult decade politics better hospital same national. Sing rate me do.",
        "until": "2030-03-22 03:33:40",
        "user": "Joseph Williams",
        "nodes": [
            "node-1",
            "node-3",
            "node-5"
        ]
    },
    {
        "_id": "0x4323",
        "todo": "Cut enter teacher campaign arrive information industry.",
        "text": "Weight like during floor suggest. White represent soldier particular country. Drug thought never with around. Culture by matter morning executive.",
        "until": "2027-07-28 12:14:44",
        "user": "Joseph Williams",
        "nodes": [
            "node-1",
            "node-3",
            "node-5"
        ]
    },
    {
        "_id": "0x4324",
        "todo": "Provide real language major prevent majority.",
        "text": "Painting different less far court exactly everybody. Forward forward society special big discover.",
        "until": "2023-09-28 16:24:11",
        "user": "Joseph Williams",
        "nodes": [
            "node-1",
            "node-3",
            "node-5"
        ]
    }
]