[
    {
        "_id": "0x447",
        "todo": "Garden and traditional foreign expect court.",
        "text": "From order street travel country another prevent. Computer open history.\nHear enter put feeling. Anything mind fish use.",
        "until": "2022-03-28 20:49:52",
        "user": "Denise Oconnell",
        "nodes": [
            "node-1",
            "node-3",
            "node-5"
        ]
    },
    {
        "_id": "0x448",
        "todo": "Lay color memory stuff hour.",
        "text": "Travel impact air one current. Although dinner week choose college. That reveal matter behind finally us. Short director eight situation these.",
        "until": "2021-05-15 16:51:53",
        "user": "Denise Oconnell",
        "nodes": [
            "node-1",
            "node-3",
            "node-5"
        ]
    },
    {
        "_id": "0x449",
        "todo": "Kind ago front hour boy show.",
        "text": "Wish home six student subject enough remain. Plan certain show morning person upon.\nArea door yes design. Themselves project call size husband miss.",
        "until": "2025-10-16 07:05:25",
        "user": "Denise Oconnell",
        "nodes": [
            "node-1",
            "node-3",
            "node-5"
        ]
    },
    {
        "_id": "0x44a",
        "todo": "Weight forget with wife go shake yeah.",
        "text": "Enjoy hold morning little fall home. Nation myself learn white heart series. Hand development human would bank exist offer sign.",
        "until": "2021-11-15 16:40:46",
        "user": "Denise Oconnell",
        "nodes": [
            "node-1",
            "node-3",
            "node-5"
        ]
    },
    {
        "_id": "0x44b",
        "todo": "Even remember choice talk require goal throughout.",
        "text": "They drug shoulder none list power suggest. Not fine than letter. Series common economy know for other artist customer.",
        "until": "2023-11-11 14:02:53",
        "user": "Denise Oconnell",
        "nodes": [
            "node-1",
            "node-3",
            "node-5"
        ]
    },
    {
        "_id": "0x44c",
        "todo": "Score point let bank.",
        "text": "Present often under right. Card why few time.\nSomething store stop shake meeting approach stop.\nMr practice finish realize put wonder. Ground apply exactly mission indeed plan right.",
        "until": "2020-08-25 22:33:33",
        "user": "Denise Oconnell",
        "nodes": [
            "node-1",
            "node-3",
            "node-5"
        ]
    }
]