[
    {
        "_id": "0x45d",
        "todo": "Benefit produce natural throw thank.",
        "text": "Idea it in. Board federal southern guess along discussion indicate. Purpose certainly want art full act.\nModel bill less door why prevent. Pressure thus baby.",
        "until": "2030-01-03 17:28:59",
        "user": "Jon Smith",
        "nodes": [
            "node-1",
            "node-3",
            "node-5"
        ]
    },
    {
        "_id": "0x45e",
        "todo": "Wind success deal agree research already represent box.",
        "text": "Technology buy stand want let. Wear order television understand force just official season.\nSpecial against short tonight mind industry every. Collection including dinner represent.",
        "until": "2028-04-22 05:37:28",
        "user": "Jon Smith",
        "nodes": [
            "node-1",
            "node-3",
            "node-5"
        ]
    },
    {
        "_id": "0x45f",
        "todo": "Radio civil idea generation kitchen per term.",
        "text": "Attention price player responsibility economic class. Great hear hard. Impact customer low should much short work.\nAlso daughter poor politics available effect clear.",
        "until": "2023-01-07 01:47:22",
        "user": "Jon Smith",
        "nodes": [
            "node-1",
            "node-3",
            "node-5"
        ]
    },
    {
        "_id": "0x460",
        "todo": "Sound able something reason PM food.",
        "text": "Cultural leg girl also. During school garden act.\nReason leg raise media law ahead rest. My end trade. Majority interesting through arrive body. Feeling world arrive on assume protect then.",
        "until": "2026-07-11 13:56:14",
        "user": "Jon Smith",
        "nodes": [
            "node-1",
            "node-3",
            "node-5"
        ]
    },
    {
        "_id": "0x461",
        "todo": "Over week toward build second while.",
        "text": "Care listen like mission seven collection various. Scientist color want old management home. Foot somebody dinner.\nHealth scientist paper season. Remember mother improve forward sure.",
        "until": "2028-04-10 04:11:48",
        "user": "Jon Smith",
        "nodes": [
            "node-1",
            "node-3",
            "node-5"
        ]
    },
    {
        "_id": "0x462",
        "todo": "Little big unit between technology.",
        "text": "Church newspaper lot serious gas.\nUp peace side various avoid option sister. Grow can use day. Care why less ten.",
        "until": "2029-03-22 23:56:16",
        "user": "Jon Smith",
        "nodes": [
            "node-1",
            "node-3",
            "node-5"
        ]
    },
    {
        "_id": "0x463",
        "todo": "Inside color road trial.",
        "text": "Air late black behavior service available establish. Decade game work actually.\nHim heart have commercial its always. Television address bit.",
        "until": "2029-04-24 04:04:07",
        "user": "Jon Smith",
        "nodes": [
            "node-1",
            "node-3",
            "node-5"
        ]
    }
]