[
    {
        "_id": "0x4c9c",
        "todo": "Likely company Congress letter modern everybody.",
        "text": "Chair modern subject degree. Term mother enjoy seven enter find low.\nOpportunity energy country them past develop city special. Result within employee show cup result. Offer purpose perhaps debate.",
        "until": "2028-06-10 03:02:44",
        "user": "Rose Smith",
        "nodes": [
            "node-1",
            "node-3",
            "node-5"
        ]
    },
    {
        "_id": "0x4c9d",
        "todo": "Mission discover national base teacher note.",
        "text": "Probably music behind father success. Partner western discover career pretty. But rather fish affect start.\nPicture out food life offer event. Tough arrive nation player rather remember program.",
        "until": "2027-03-03 10:15:07",
        "user": "Rose Smith",
        "nodes": [
            "node-1",
            "node-3",
            "node-5"
        ]
    },
    {
        "_id": "0x4c9e",
        "todo": "Together short gas sense price result bad despite.",
        "text": "Young rest word arrive check since poor also. Bill end crime left.\nSit most security style. Wide debate about expect let seat range. Over open research compare.",
        "until": "2026-10-27 08:23:34",
        "user": "Rose Smith",
        "nodes": [
            "node-1",
            "node-3",
            "node-5"
        ]
    },
    {
        "_id": "0x4c9f",
        "todo": "Fall cause will similar report make area.",
        "text": "Money style member begin range. Game in more lawyer way.\nTrip life middle task gas personal road. Quite letter plant win hair.\nKey myself second light. Put feeling these.",
        "until": "2023-03-26 00:48:08",
        "user": "Rose Smith",
        "nodes": [
            "node-1",
            "node-3",
            "node-5"
        ]
    },
    {
        "_id": "0x4ca0",
        "todo": "She manage five relationship attorney.",
        "text": "Any term might anything attention light.",
        "until": "2029-03-14 22:01:13",
        "user": "Rose Smith",
        "nodes": [
            "node-1",
            "node-3",
            "node-5"
        ]
    },
    {
        "_id": "0x4ca1",
        "todo": "Behind win red news.",
        "text": "Source western wrong start lot. Catch authority TV trouble. It despite population last off full.\nHappy information develop phone. Dream issue want adult. Ahead thank win hotel let walk.",
        "until": "2021-08-16 22:31:18",
        "user": "Rose Smith",
        "nodes": [
            "node-1",
            "node-3",
            "node-5"
        ]
    },
    {
        "_id": "0x4ca2",
        "todo": "Mother plant military drop course born Mr three.",
        "text": "Class plant sister role full cell huge. Plan that investment.\nCan benefit case throw. Will point admit across I increase learn.",
        "until": "2021-11-09 14:45:20",
        "user": "Rose Smith",
        "nodes": [
            "node-1",
            "node-3",
            "node-5"
        ]
    }
]