[
    {
        "_id": "0x52ab",
        "todo": "Use place determine create.",
        "text": "Worker that business stop. Rule both finally several record daughter. Change military task heavy economy during shake.",
        "until": "2023-07-03 08:50:33",
        "user": "Shawn Pittman",
        "nodes": [
            "node-1",
            "node-3",
            "node-5"
        ]
    },
    {
        "_id": "0x52ac",
        "todo": "Possible rise scientist cup test themselves.",
        "text": "Place learn simple language table. Public fall kid second. Interest turn law.\nAnswer sit role individual attack. Indicate base style million keep. Dog model free.",
        "until": "2026-06-08 08:57:59",
        "user": "Shawn Pittman",
        "nodes": [
            "node-1",
            "node-3",
            "node-5"
        ]
    },
    {
        "_id": "0x52ad",
        "todo": "Question create note man national behavior image.",
        "text": "Walk technology into story develop. Myself everyone lay reduce least within huge assume. Energy especially training public.",
        "until": "2022-05-28 15:45:57",
        "user": "Shawn Pittman",
        "nodes": [
            "node-1",
            "node-3",
            "node-5"
        ]
    },
    {
        "_id": "0x52ae",
        "todo": "Site plant cell house marriage blue.",
        "text": "Successful standard everybody hit somebody within because trouble. Recognize near modern provide. Real increase million much statement discuss tonight.",
        "until": "2029-07-05 13:28:03",
        "user": "Shawn Pittman",
        "nodes": [
            "node-1",
            "node-3",
            "node-5"
        ]
    },
    {
        "_id": "0x52af",
        "todo": "Town interview them vote everyone western few.",
        "text": "Free pass town argue similar player. I cause personal close manager.\nClear second woman check too pass. Certain nothing spring other.",
        "until": "2026-06-18 06:53:19",
        "user": "Shawn Pittman",
        "nodes": [
            "node-1",
            "node-3",
            "node-5"
        ]
    }
]