[
    {
        "_id": "0x56f4",
        "todo": "Stock baby human argue half compare fall.",
        "text": "Staff yard in easy. Small accept meet attorney discussion. Small main difference conference despite perform debate probably. Condition anyone leader off such argue.",
        "until": "2024-01-14 11:28:23",
        "user": "Martha King",
        "nodes": [
            "node-1",
            "node-3",
            "node-5"
        ]
    },
    {
        "_id": "0x56f5",
        "todo": "Rock man top more sort.",
        "text": "Here page minute they call reduce. Drop management four protect new marriage entire mother. Strong call notice group argue.",
        "until": "2020-06-04 18:44:35",
        "user": "Martha King",
        "nodes": [
            "node-1",
            "node-3",
            "node-5"
        ]
    },
    {
        "_id": "0x56f6",
        "todo": "Agreement possible system beat cause.",
        "text": "Respond science throw goal total hundred. Question across account Democrat must. Month skin choice ability.\nTax blue price quickly too. Really again his.",
        "until": "2020-10-30 13:05:26",
        "user": "Martha King",
        "nodes": [
            "node-1",
            "node-3",
            "node-5"
        ]
    },
    {
        "_id": "0x56f7",
        "todo": "Town skill develop case ground.",
        "text": "Fund itself per start.\nRecord story four majority. Cell base much whose box have. Although pick just fly professional.",
        "until": "2023-06-10 10:10:51",
        "user": "Martha King",
        "nodes": [
            "node-1",
            "node-3",
            "node-5"
        ]
    }
]