[
    {
        "_id": "0x5b88",
        "todo": "Agency because every picture run.",
        "text": "Unit day high detail. Both claim miss easy. Fish cost goal tax heart already fine.",
        "until": "2029-02-06 06:12:36",
        "user": "Jessica Juarez",
        "nodes": [
            "node-1",
            "node-3",
            "node-5"
        ]
    },
    {
        "_id": "0x5b89",
        "todo": "Relationship agreement establish guy simply leave find.",
        "text": "Professional suggest type while fine tax candidate. Early their recent base sometimes tax majority. Manager serious up measure.\nSuch return sit. Occur these long.",
        "until": "2022-10-19 15:15:00",
        "user": "Jessica Juarez",
        "nodes": [
            "node-1",
            "node-3",
            "node-5"
        ]
    },
    {
        "_id": "0x5b8a",
        "todo": "Material director someone house thought soon stay.",
        "text": "Since edge hear serve trip give. Do hear write.\nBlue Mrs main send most short eye act. Really letter decision until mission out enjoy.",
        "until": "2024-01-10 09:44:26",
        "user": "Jessica Juarez",
        "nodes": [
            "node-1",
            "node-3",
            "node-5"
        ]
    },
    {
        "_id": "0x5b8b",
        "todo": "Short large increase article.",
        "text": "More trade top rise hot well them. Us run ok player medical. Chance support decide during.\nRecently small person ago. Industry single single economy.",
        "until": "2029-09-05 06:23:06",
        "user": "Jessica Juarez",
        "nodes": [
            "node-1",
            "node-3",
            "node-5"
        ]
    },
    {
        "_id": "0x5b8c",
        "todo": "Argue foreign set include parent this.",
        "text": "Again quickly worry bed himself me. Human spend investment hand next.",
        "until": "2021-01-25 06:17:06",
        "user": "Jessica Juarez",
        "nodes": [
            "node-1",
            "node-3",
            "node-5"
        ]
    }
]