[
    {
        "_id": "0x6d4f",
        "todo": "Congress look race product wife.",
        "text": "Other property area line probably art statement. Account effect factor.\nRealize manager society human apply for nation piece.",
        "until": "2026-12-31 16:22:34",
        "user": "Janice Brady",
        "nodes": [
            "node-1",
            "node-3",
            "node-5"
        ]
    },
    {
        "_id": "0x6d50",
        "todo": "Talk evidence continue.",
        "text": "Produce might conference plant drive teacher. Decide matter only especially light material measure.",
        "until": "2028-12-16 01:33:53",
        "user": "Janice Brady",
        "nodes": [
            "node-1",
            "node-3",
            "node-5"
        ]
    }
]