[
    {
        "_id": "0x74aa",
        "todo": "Cell foot list exactly kid single name.",
        "text": "Ahead TV serious administration. Might seem contain cultural. Along born today summer.\nMajor question world newspaper generation whether really language. Even north else market from that book man.",
        "until": "2020-09-08 09:59:13",
        "user": "Erica Edwards",
        "nodes": [
            "node-1",
            "node-3",
            "node-5"
        ]
    },
    {
        "_id": "0x74ab",
        "todo": "Candidate little size threat.",
        "text": "Notice month environmental much organization now.\nThroughout its pressure according. Professional sit at current likely she hard.",
        "until": "2022-10-11 21:36:12",
        "user": "Erica Edwards",
        "nodes": [
            "node-1",
            "node-3",
            "node-5"
        ]
    },
    {
        "_id": "0x74ac",
        "todo": "Young space theory.",
        "text": "Capital defense pay treat course. Again system up up use hair region girl.\nMuch rise hope season cell together across. War cup two ok glass eat.",
        "until": "2027-10-07 10:44:19",
        "user": "Erica Edwards",
        "nodes": [
            "node-1",
            "node-3",
            "node-5"
        ]
    },
    {
        "_id": "0x74ad",
        "todo": "Attorney wall card include reduce name.",
        "text": "Allow general his contain benefit medical. Cup difficult try middle stock.\nShare step relate car. Another forward answer despite night treatment. Ago pass movement raise enough consider more.",
        "until": "2023-10-20 22:49:06",
        "user": "Erica Edwards",
        "nodes": [
            "node-1",
            "node-3",
            "node-5"
        ]
    },
    {
        "_id": "0x74ae",
        "todo": "Effect reason expert employee lawyer.",
        "text": "Down summer art condition. Bring everything return ago skin report. Friend open public.\nPopulation learn enter reflect artist carry radio. Law product tree voice give.",
        "until": "2029-11-15 18:05:13",
        "user": "Erica Edwards",
        "nodes": [
            "node-1",
            "node-3",
            "node-5"
        ]
    },
    {
        "_id": "0x74af",
        "todo": "Charge draw age do method.",
        "text": "Budget carry threat where person college. Anything single hair range.\nSite board hear because. Prove PM be never development nor could only. Above little check Democrat Mr suddenly.",
        "until": "2027-11-08 21:06:33",
        "user": "Erica Edwards",
        "nodes": [
            "node-1",
            "node-3",
            "node-5"
        ]
    },
    {
        "_id": "0x74b0",
        "todo": "Sea scientist dinner board sign.",
        "text": "Music seven green age. Nothing century join type. See why leader analysis nearly.\nBack western step. Item address threat. Dark might raise wrong which his.\nHave cold generation evening team.",
        "until": "2025-12-06 18:05:26",
        "user": "Erica Edwards",
        "nodes": [
            "node-1",
            "node-3",
            "node-5"
        ]
    },
    {
        "_id": "0x74b1",
        "todo": "Parent region woman gas tough American.",
        "text": "Reach take determine yard business policy. Area receive audience marriage. Start evening heart because. Glass dog foreign author page former pull take.",
        "until": "2022-02-23 23:23:34",
        "user": "Erica Edwards",
        "nodes": [
            "node-1",
            "node-3",
            "node-5"
        ]
    }
]