[
    {
        "_id": "0x8ce4",
        "todo": "That play rich pick where.",
        "text": "Become minute marriage amount drop. Customer performance television bring enter would.",
        "until": "2026-11-09 04:49:56",
        "user": "Alexandra Adams",
        "nodes": [
            "node-1",
            "node-3",
            "node-5"
        ]
    },
    {
        "_id": "0x8ce5",
        "todo": "Woman question range blue their.",
        "text": "Data technology father theory. Relationship successful upon at heart agree. Ago if wear find six mother there. Read hear happen reason.",
        "until": "2030-04-18 20:13:41",
        "user": "Alexandra Adams",
        "nodes": [
            "node-1",
            "node-3",
            "node-5"
        ]
    },
    {
        "_id": "0x8ce6",
        "todo": "Billion be new paper.",
        "text": "Face phone than opportunity. Building actually international oil break camera window. Answer foot medical.",
        "until": "2026-06-05 15:51:39",
        "user": "Alexandra Adams",
        "nodes": [
            "node-1",
            "node-3",
            "node-5"
        ]
    },
    {
        "_id": "0x8ce7",
        "todo": "Range evening make any anyone wrong.",
        "text": "Present central look central girl clear rule. Piece dinner could fly.\nSon draw hit law pick sound.",
        "until": "2027-03-06 03:46:38",
        "user": "Alexandra Adams",
        "nodes": [
            "node-1",
            "node-3",
            "node-5"
        ]
    },
    {
        "_id": "0x8ce8",
        "todo": "History hotel already.",
        "text": "Inside result tell production instead study guy again. Huge hundred various mother. Choose two may challenge.",
        "until": "2025-03-17 22:30:31",
        "user": "Alexandra Adams",
        "nodes": [
            "node-1",
            "node-3",
            "node-5"
        ]
    },
    {
        "_id": "0x8ce9",
        "todo": "Professor compare theory public.",
        "text": "Sign life blood pull. Performance somebody simple budget shoulder political. Cold note set serious.",
        "until": "2029-03-15 03:30:10",
        "user": "Alexandra Adams",
        "nodes": [
            "node-1",
            "node-3",
            "node-5"
        ]
    },
    {
        "_id": "0x8cea",
        "todo": "Affect other nice hear.",
        "text": "Explain power couple season decide. Long despite everything group free positive.\nMyself friend compare general campaign mind effect. Behavior this admit American heart kid. Exactly develop again go.",
        "until": "2020-07-16 12:53:15",
        "user": "Alexandra Adams",
        "nodes": [
            "node-1",
            "node-3",
            "node-5"
        ]
    },
    {
        "_id": "0x8ceb",
        "todo": "Surface build entire authority.",
        "text": "Available history do condition ago. Reach close style consider.\nLive mind end act spring. Tell to throughout never health.\nSubject pull letter line fly.",
        "until": "2028-02-12 11:27:19",
        "user": "Alexandra Adams",
        "nodes": [
            "node-1",
            "node-3",
            "node-5"
        ]
    }
]