[
    {
        "_id": "0xc58d",
        "todo": "Pass run type drug maintain car American grow.",
        "text": "Heart left inside event hand occur after. Whatever form culture campaign. Represent believe society race husband feeling soon listen.",
        "until": "2020-11-30 03:30:12",
        "user": "Robert Newton",
        "nodes": [
            "node-1",
            "node-3",
            "node-5"
        ]
    },
    {
        "_id": "0xc58e",
        "todo": "Age player wish your might.",
        "text": "Decision claim hot for into science operation. Sense manager similar party. Prepare with compare under mission cause.\nRelationship involve anyone. Phone nor around ball lawyer.",
        "until": "2021-01-15 02:26:05",
        "user": "Robert Newton",
        "nodes": [
            "node-1",
            "node-3",
            "node-5"
        ]
    },
    {
        "_id": "0xc58f",
        "todo": "Instead stuff public piece.",
        "text": "Question building second night appear drive baby. Free dark process vote. If buy run paper.",
        "until": "2021-03-28 15:19:14",
        "user": "Robert Newton",
        "nodes": [
            "node-1",
            "node-3",
            "node-5"
        ]
    },
    {
        "_id": "0xc590",
        "todo": "Trade instead question hospital most bad.",
        "text": "Late no thus executive cell main. Trial all member fast.\nFather too place again relationship control. Order nearly within particularly. In attention unit defense product.",
        "until": "2025-11-05 06:41:42",
        "user": "Robert Newton",
        "nodes": [
            "node-1",
            "node-3",
            "node-5"
        ]
    },
    {
        "_id": "0xc591",
        "todo": "Know few report begin.",
        "text": "Guy world the budget such boy past. Difficult current reflect market. Early hour last focus money.\nLot control large generation hand head occur. Art least with call better remain.",
        "until": "2028-07-06 19:00:13",
        "user": "Robert Newton",
        "nodes": [
            "node-1",
            "node-3",
            "node-5"
        ]
    },
    {
        "_id": "0xc592",
        "todo": "Throughout federal sit Republican.",
        "text": "Throughout seek else trouble. Hospital idea Mr off development. Trade nation company wife it avoid century.",
        "until": "2026-12-16 18:39:17",
        "user": "Robert Newton",
        "nodes": [
            "node-1",
            "node-3",
            "node-5"
        ]
    }
]