[
    {
        "_id": "0xc9ab",
        "todo": "Raise as myself will choose side.",
        "text": "Attention throw much red. Instead reason surface reach.\nLearn road head such even. Group parent both thus soldier second agency. This parent fund sound president open.",
        "until": "2026-04-25 14:44:00",
        "user": "Leslie Hayes",
        "nodes": [
            "node-1",
            "node-3",
            "node-5"
        ]
    },
    {
        "_id": "0xc9ac",
        "todo": "Thought behind feel degree fine.",
        "text": "Order network high receive carry morning social. Crime need two everything evidence reduce.",
        "until": "2023-01-14 22:49:44",
        "user": "Leslie Hayes",
        "nodes": [
            "node-1",
            "node-3",
            "node-5"
        ]
    },
    {
        "_id": "0xc9ad",
        "todo": "Beat glass line market star sing.",
        "text": "Western baby computer treat standard black hot. Kind career throw.\nEstablish event defense son exactly fish. Line commercial produce particular reach smile. Member seek into message figure dinner.",
        "until": "2021-06-01 23:46:02",
        "user": "Leslie Hayes",
        "nodes": [
            "node-1",
            "node-3",
            "node-5"
        ]
    },
    {
        "_id": "0xc9ae",
        "todo": "In many above rather.",
        "text": "Issue else about report walk have. Friend require but drug myself able establish.\nBed whose student plan relationship successful. Party house price two fight.",
        "until": "2030-03-20 06:29:18",
        "user": "Leslie Hayes",
        "nodes": [
            "node-1",
            "node-3",
            "node-5"
        ]
    },
    {
        "_id": "0xc9af",
        "todo": "Benefit must able action.",
        "text": "Sport history fill middle room. Family once response sound be possible memory. Rise car want window purpose.",
        "until": "2026-08-08 02:56:50",
        "user": "Leslie Hayes",
        "nodes": [
            "node-1",
            "node-3",
            "node-5"
        ]
    },
    {
        "_id": "0xc9b0",
        "todo": "Individual last dream model provide.",
        "text": "May side edge size. Head long who first national. Prove day cell poor stay few.\nElse reduce hear should beat significant once. Her while so leave serve everything.",
        "until": "2025-01-15 10:41:35",
        "user": "Leslie Hayes",
        "nodes": [
            "node-1",
            "node-3",
            "node-5"
        ]
    }
]