[
    {
        "_id": "0xd5f6",
        "todo": "Mouth off sister magazine think.",
        "text": "Heavy economy development fight camera purpose. Free while morning tough.\nArm writer act recognize check process rich his. Decide stuff finally yard play food factor indicate.",
        "until": "2029-12-30 07:30:44",
        "user": "Rachael Smith",
        "nodes": [
            "node-1",
            "node-3",
            "node-5"
        ]
    },
    {
        "_id": "0xd5f7",
        "todo": "Tend everyone information operation music.",
        "text": "Positive lead goal against.\nGo where school laugh. Trade technology save a wind whose. Still picture nation down we once. Account edge never since even.",
        "until": "2026-11-28 11:47:50",
        "user": "Rachael Smith",
        "nodes": [
            "node-1",
            "node-3",
            "node-5"
        ]
    },
    {
        "_id": "0xd5f8",
        "todo": "Own agreement myself bad.",
        "text": "Arm live turn your between door institution. State represent local responsibility summer box.",
        "until": "2028-10-11 16:57:53",
        "user": "Rachael Smith",
        "nodes": [
            "node-1",
            "node-3",
            "node-5"
        ]
    },
    {
        "_id": "0xd5f9",
        "todo": "Leg shoulder audience wind.",
        "text": "Ability husband church common movement about training. When television remain fall. My sea to simply once.",
        "until": "2020-09-14 16:55:06",
        "user": "Rachael Smith",
        "nodes": [
            "node-1",
            "node-3",
            "node-5"
        ]
    },
    {
        "_id": "0xd5fa",
        "todo": "About wrong day manager dog.",
        "text": "Kid hand fine although technology by. Language wide color follow task.\nIdea ability policy mother smile food. Full action some worry dark. Tax himself letter indeed offer probably.",
        "until": "2029-02-11 23:14:21",
        "user": "Rachael Smith",
        "nodes": [
            "node-1",
            "node-3",
            "node-5"
        ]
    },
    {
        "_id": "0xd5fb",
        "todo": "Bill source clear.",
        "text": "Television rich street. Those within building smile discussion thousand agency. Middle type million third popular form relate. Report bed bar word peace suffer.",
        "until": "2028-08-27 19:05:51",
        "user": "Rachael Smith",
        "nodes": [
            "node-1",
            "node-3",
            "node-5"
        ]
    }
]