[
    {
        "_id": "0xfb",
        "todo": "Successful bed feeling benefit world store.",
        "text": "Technology significant campaign process cultural. Beyond thank every every.\nCertainly second chance option. Woman huge region decade instead few.",
        "until": "2025-01-06 05:47:40",
        "user": "Richard Sparks",
        "nodes": [
            "node-1",
            "node-3",
            "node-5"
        ]
    },
    {
        "_id": "0xfc",
        "todo": "Several write protect indicate mouth organization.",
        "text": "Year unit money mean follow into than. Learn speech friend possible rule there.\nView federal young offer little. At nearly bring trip spend heavy resource.",
        "until": "2024-09-25 20:58:09",
        "user": "Richard Sparks",
        "nodes": [
            "node-1",
            "node-3",
            "node-5"
        ]
    },
    {
        "_id": "0xfd",
        "todo": "Choose suggest measure fill.",
        "text": "Person reveal statement food road care every. Design ever other social thing thing. Sometimes blood paper building.\nPresent here suffer affect at item one. Although agent order seem heart loss.",
        "until": "2022-04-06 08:07:24",
        "user": "Richard Sparks",
        "nodes": [
            "node-1",
            "node-3",
            "node-5"
        ]
    },
    {
        "_id": "0xfe",
        "todo": "To recent nation lead across total.",
        "text": "Here western arrive realize old. Movie despite get action myself. Eye camera whole drug.\nSomething especially here management. List after less room. Usually feel north wind doctor stuff score.",
        "until": "2022-03-08 12:28:11",
        "user": "Richard Sparks",
        "nodes": [
            "node-1",
            "node-3",
            "node-5"
        ]
    },
    {
        "_id": "0xff",
        "todo": "New worry else service must drive.",
        "text": "Away suffer down perform know kitchen for. Education law successful four purpose case Democrat thousand.\nGrowth themselves wrong education hard air author. Left production day cut past several.",
        "until": "2028-02-20 17:20:14",
        "user": "Richard Sparks",
        "nodes": [
            "node-1",
            "node-3",
            "node-5"
        ]
    },
    {
        "_id": "0x100",
        "todo": "If your image scientist through.",
        "text": "Drop environmental stop community everybody. Challenge particularly position main. Everybody movie happy very form idea positive.",
        "until": "2029-11-06 06:40:02",
        "user": "Richard Sparks",
        "nodes": [
            "node-1",
            "node-3",
            "node-5"
        ]
    }
]